twython/__init__.py
twython/advisory.py
twython/api.py
twython/compat.py
twython/endpoints.py
twython/exceptions.py
twython/helpers.py
twython/streaming/__init__.py
twython/streaming/api.py
twython/streaming/types.py
twython-3.9.0.dist-info/AUTHORS.rst
twython-3.9.0.dist-info/LICENSE
twython-3.9.0.dist-info/METADATA
twython-3.9.0.dist-info/WHEEL
twython-3.9.0.dist-info/top_level.txt
twython-3.9.0.dist-info/RECORD
