Metadata-Version: 2.1
Name: twython
Version: 3.9.0
Summary: Actively maintained, pure Python wrapper for the Twitter API. Supports both normal and streaming Twitter APIs
Home-page: https://github.com/ryanmcgrath/twython/tree/master
Author: Ryan McGrath
Author-email: ryan@rymc.io
License: MIT
Keywords: twitter search api tweet twython stream
Platform: UNKNOWN
Classifier: Development Status :: 4 - Beta
Classifier: Intended Audience :: Developers
Classifier: License :: OSI Approved :: MIT License
Classifier: Topic :: Software Development :: Libraries :: Python Modules
Classifier: Topic :: Communications :: Chat
Classifier: Topic :: Internet
Classifier: Programming Language :: Python
Classifier: Programming Language :: Python :: 2.7
Classifier: Programming Language :: Python :: 3
Classifier: Programming Language :: Python :: 3.5
Classifier: Programming Language :: Python :: 3.6
Classifier: Programming Language :: Python :: 3.7
Requires-Dist: requests (>=2.1.0)
Requires-Dist: requests-oauthlib (>=0.4.0)
